<?xml version="1.0"?>
<metaproxy xmlns="http://indexdata.com/metaproxy" version="1.0">
  <dlpath>/usr/lib64/metaproxy4/modules</dlpath>
  <start route="start"/>
  <filters>
    <filter id="frontend" type="frontend_net">
      <threads>50</threads>
      <port>@:9000</port>
      <include src="ports.d/*.xml"/>
      <!-- Uncomment the message below to get queue/thread usage logging -->
      <message>FN</message>
    </filter>
  </filters>
  <routes>
    <route id="start">
      <filter refid="frontend"/>
      <include src="filters-enabled/*.xml"/>
      <filter type="bounce"/>
    </route>
    <include src="routes.d/*.xml"/>
  </routes>
</metaproxy>

